README.md
setup.py
pruebas/__init__.py
sbs_gob_pe_helper/CuponCero.py
sbs_gob_pe_helper/IndiceSpreadsCorporativo.py
sbs_gob_pe_helper/VectorPrecioRentaFija.py
sbs_gob_pe_helper/__init__.py
sbs_gob_pe_helper/common.py
sbs_gob_pe_helper/seleniumbase_test.py
sbs_gob_pe_helper.egg-info/PKG-INFO
sbs_gob_pe_helper.egg-info/SOURCES.txt
sbs_gob_pe_helper.egg-info/dependency_links.txt
sbs_gob_pe_helper.egg-info/entry_points.txt
sbs_gob_pe_helper.egg-info/requires.txt
sbs_gob_pe_helper.egg-info/top_level.txt