Metadata-Version: 2.1
Name: sbs-gob-pe-helper
Version: 0.0.7
Summary: sbs-gob-pe-helper para proyectos de análisis financiero
Download-URL: https://URL_PAQUETE/sbs-gob-pe-helper/-/archive/master/sbs-gob-pe-helper-master.tar
Author: Erik Carl Candela Rojas
Author-email: erik.candela.rojas@gmail.com
License: NOTFOUND
Keywords: sbs-gob-pe-helper,paquete,package,sbs web scraping,curva cupon cero,Vector Precio Renta Fija,Indice Spreads Corporativo
Classifier: Development Status :: 4 - Beta
Classifier: Intended Audience :: Developers
Classifier: Topic :: Software Development :: Build Tools
Classifier: Programming Language :: Python :: 3.7
Requires-Dist: pandas>=1.5.3
Requires-Dist: numpy>=1.24.4
Requires-Dist: pyxlsb>=1.0.9
Requires-Dist: openpyxl>=3.0.7
Requires-Dist: beautifulsoup4>=4.12.3
